darkgreybox/__init__.py
darkgreybox/base_model.py
darkgreybox/fit.py
darkgreybox/models.py
darkgreybox/predict.py
darkgreybox/prefit.py
darkgreybox/train.py
darkgreybox-0.3.2.dist-info/LICENSE
darkgreybox-0.3.2.dist-info/METADATA
darkgreybox-0.3.2.dist-info/WHEEL
darkgreybox-0.3.2.dist-info/top_level.txt
darkgreybox-0.3.2.dist-info/RECORD
