Metadata-Version: 2.1
Name: darkgreybox
Version: 0.3.2
Summary: DarkGreyBox: An Open-Source Data-Driven Python Building Thermal Model Inspired By Genetic Algorithms and Machine Learning
Home-page: https://github.com/czagoni/darkgreybox
Author: csaba zagoni
Author-email: czagoni@greenpeace.org
License: UNKNOWN
Download-URL: https://github.com/czagoni/darkgreybox/archive/refs/tags/0.3.1.tar.gz
Keywords: python model thermal machine-learning genetic-algorithm data-science
Platform: UNKNOWN
Classifier: Development Status :: 5 - Production/Stable
Classifier: Intended Audience :: Developers
Classifier: Intended Audience :: Science/Research
Classifier: Programming Language :: Python :: 3
Classifier: Programming Language :: Python :: 3.8
Classifier: License :: OSI Approved :: GNU General Public License v3 (GPLv3)
Requires-Dist: lmfit (<2,>=1.1.0)
Requires-Dist: pandas (<3,>=1.5.2)
Requires-Dist: joblib (<2,>=1.2.0)
Provides-Extra: dev
Requires-Dist: statsmodels (~=0.13.1) ; extra == 'dev'
Requires-Dist: numdifftools (~=0.9.39) ; extra == 'dev'
Requires-Dist: scikit-learn (~=1.2.0) ; extra == 'dev'
Requires-Dist: matplotlib (~=3.6.3) ; extra == 'dev'
Requires-Dist: jupyter (~=1.0.0) ; extra == 'dev'
Requires-Dist: notebook (~=6.5.2) ; extra == 'dev'
Requires-Dist: autopep8 (~=2.0.1) ; extra == 'dev'
Requires-Dist: isort (~=5.11.4) ; extra == 'dev'
Provides-Extra: test
Requires-Dist: flake8 (~=6.0.0) ; extra == 'test'
Requires-Dist: pytest (~=7.2.1) ; extra == 'test'
Requires-Dist: pytest-mock (~=3.10.0) ; extra == 'test'
Requires-Dist: pytest-cov (~=4.0.0) ; extra == 'test'
